obis_laser_controller/__init__.py
obis_laser_controller/obis_laser_controller.py
obis_laser_controller-0.0.1.dist-info/LICENSE
obis_laser_controller-0.0.1.dist-info/METADATA
obis_laser_controller-0.0.1.dist-info/WHEEL
obis_laser_controller-0.0.1.dist-info/top_level.txt
obis_laser_controller-0.0.1.dist-info/RECORD
