Metadata-Version: 2.1
Name: obis-laser-controller
Version: 0.0.1
Summary: Controller for OBIS Lasers.
Home-page: UNKNOWN
Author: Brian Carlsen
Author-email: carlsen.bri@gmail.com
License: UNKNOWN
Platform: UNKNOWN
Classifier: Programming Language :: Python :: 3
Classifier: Operating System :: OS Independent
Classifier: License :: OSI Approved :: GNU General Public License v3 (GPLv3)
Classifier: Development Status :: 3 - Alpha
Requires-Dist: easy-scpi (>=0.0.9)
